<?xml version="1.0" encoding="UTF-8"?>
<?xml-stylesheet type="text/xsl" href="forest.xsl"?>
<tree expanded="true" show-heading="true" show-metadata="true" toc="false" numbered="false" root="false"><frontmatter><anchor>1174</anchor> <taxon>Proposition</taxon> <addr>sga1-i.7.1</addr><route>sga1-i.7.1.xml</route>     <number>I.7.1</number> <parent>sga1-i.7</parent> </frontmatter> <mainmatter><p/></mainmatter> <backmatter><contributions/> <context><tree expanded="false" show-heading="true" show-metadata="true" toc="false" numbered="false" root="false"><frontmatter><anchor>1175</anchor> <taxon>Section</taxon> <addr>sga1-i.7</addr><route>sga1-i.7.xml</route>    <title><link href="sga1-i.xml" type="local" addr="sga1-i" title="SGA 1: Étale covers and the fundamental group › Étale morphisms"><link href="sga1.xml" type="local" addr="sga1" title="SGA 1: Étale covers and the fundamental group">SGA 1: Étale covers and the fundamental group</link> › Étale morphisms</link> › Local construction of unramified and étale morphisms</title> <number>I.7</number> <parent>sga1-i</parent> </frontmatter> <mainmatter><tree expanded="true" show-heading="true" show-metadata="false" toc="true" numbered="false" root="false"><frontmatter><anchor>1176</anchor> <taxon>Proposition</taxon> <addr>sga1-i.7.1</addr><route>sga1-i.7.1.xml</route>     <number>I.7.1</number> <parent>sga1-i.7</parent> </frontmatter> <mainmatter><p/></mainmatter> </tree></mainmatter> </tree></context> <related><tree expanded="false" show-heading="true" show-metadata="true" toc="false" numbered="false" root="false"><frontmatter><anchor>1177</anchor> <taxon>Section</taxon> <addr>sga1-i.7</addr><route>sga1-i.7.xml</route>    <title><link href="sga1-i.xml" type="local" addr="sga1-i" title="SGA 1: Étale covers and the fundamental group › Étale morphisms"><link href="sga1.xml" type="local" addr="sga1" title="SGA 1: Étale covers and the fundamental group">SGA 1: Étale covers and the fundamental group</link> › Étale morphisms</link> › Local construction of unramified and étale morphisms</title> <number>I.7</number> <parent>sga1-i</parent> </frontmatter> <mainmatter><tree expanded="true" show-heading="true" show-metadata="false" toc="true" numbered="false" root="false"><frontmatter><anchor>1178</anchor> <taxon>Proposition</taxon> <addr>sga1-i.7.1</addr><route>sga1-i.7.1.xml</route>     <number>I.7.1</number> <parent>sga1-i.7</parent> </frontmatter> <mainmatter><p/></mainmatter> </tree></mainmatter> </tree></related> <backlinks/> <references/></backmatter></tree>